MANIFEST.in
README.md
pyproject.toml
setup.py
./pysamstats/__init__.py
./pysamstats/binned.py
./pysamstats/config.py
./pysamstats/io.py
./pysamstats/pileup.py
./pysamstats/util.py
./pysamstats/test/__init__.py
./pysamstats/test/test_binned.py
./pysamstats/test/test_io.py
./pysamstats/test/test_pileup.py
./pysamstats/test/test_regression.py
./pysamstats/test/util.py
pysamstats/opt.c
pysamstats/opt.pyx
pysamstats.egg-info/PKG-INFO
pysamstats.egg-info/SOURCES.txt
pysamstats.egg-info/dependency_links.txt
pysamstats.egg-info/requires.txt
pysamstats.egg-info/top_level.txt
scripts/pysamstats