Metadata-Version: 1.1
Name: pysamstats
Version: 1.1.1
Summary: A Python utility for calculating statistics against genome position based on sequence alignments from a SAM, BAM or CRAM file.
Home-page: https://github.com/alimanfoo/pysamstats
Author: Alistair Miles
Author-email: alimanfoo@googlemail.com
License: MIT Licenses
Platform: UNKNOWN
Classifier: Intended Audience :: Developers
Classifier: License :: OSI Approved :: MIT License
Classifier: Programming Language :: Python :: 2.7
Classifier: Programming Language :: Python :: 3.5
Classifier: Programming Language :: Python :: 3.6
Classifier: Programming Language :: Python :: 3.7
Classifier: Topic :: Software Development :: Libraries :: Python Modules
